.DS_Store
batch/__init__.py
batch/plus_batch.py
database/__init__.py
database/plus_database.py
helper/__init__.py
helper/plus_helper.py
msg_queue/__init__.py
msg_queue/plus_msg_queue.py
plus_dataframe/__init__.py
plus_dataframe/plus_dataframe.py
storage/__init__.py
storage/plus_storage.py
subbatch/__init__.py
subbatch/plus_subbatch.py
web_service/__init__.py
web_service/plus_web_service.py
plus_bi_main-0.5.5.dist-info/LICENSE
plus_bi_main-0.5.5.dist-info/METADATA
plus_bi_main-0.5.5.dist-info/WHEEL
plus_bi_main-0.5.5.dist-info/top_level.txt
plus_bi_main-0.5.5.dist-info/RECORD
