Metadata-Version: 2.1
Name: plus-bi-main
Version: 0.5.5
Summary: Plus BI modules
Home-page: https://gitlab.com/mvdg_dsc/nl-plus-bi-main-modules
Author: Pascal van de Pol
Author-email: pascal@vandepol.tweak.nl
License: MIT
Platform: UNKNOWN
Classifier: Programming Language :: Python :: 3
Classifier: License :: OSI Approved :: MIT License
Classifier: Operating System :: OS Independent
Requires-Python: >=3.7
